tokipona/__init__.py
tokipona/makeStatistics.py
tokipona/makeTexts.py
tokipona/makeVimSyntax.py
tokipona/makeWordnet.py
tokipona/utils.py
tokipona-0.1b0.dist-info/DESCRIPTION.rst
tokipona-0.1b0.dist-info/METADATA
tokipona-0.1b0.dist-info/RECORD
tokipona-0.1b0.dist-info/WHEEL
tokipona-0.1b0.dist-info/metadata.json
tokipona-0.1b0.dist-info/top_level.txt
